{
	"format_version": "1.12.0",
	"minecraft:geometry": [
		{
			"description": {
				"identifier": "geometry.unknown",
				"texture_width": 64,
				"texture_height": 64,
				"visible_bounds_width": 3,
				"visible_bounds_height": 2.5,
				"visible_bounds_offset": [0, 0.75, 0]
			},
			"bones": [
				{
					"name": "bb_main",
					"pivot": [0, 0, 0],
					"cubes": [
						{"origin": [-6, 0, -8], "size": [12, 7, 16], "uv": [0, 0]},
						{"origin": [1, 0.5, -4], "size": [5, 6, 11], "pivot": [0, 0.5, 4], "rotation": [0, -20, 0], "uv": [0, 23]},
						{"origin": [-6, 0.5, -4], "size": [5, 6, 11], "pivot": [0, 0.5, 4], "rotation": [0, 20, 0], "uv": [0, 23], "mirror": true},
						{"origin": [-4, 2, -6], "size": [8, 6, 9], "pivot": [0, -1, -2], "rotation": [-10, 0, 0], "uv": [23, 31]}
					]
				},
				{
					"name": "bone2",
					"pivot": [3.5, 6.5, 4.75],
					"rotation": [-49.65098, -31.3213, 16.48457],
					"cubes": [
						{"origin": [2, 5, 3.25], "size": [3, 3, 3], "uv": [46, 46]}
					]
				},
				{
					"name": "bone3",
					"pivot": [-3.5, 6.5, 4.75],
					"rotation": [-49.65098, 31.3213, -16.48457],
					"cubes": [
						{"origin": [-5, 5, 3.25], "size": [3, 3, 3], "uv": [30, 46]}
					]
				},
				{
					"name": "bone",
					"pivot": [0, 7.00049, -4.63769],
					"rotation": [-40, 0, 0],
					"cubes": [
						{"origin": [-3, 4.00049, -7.63769], "size": [6, 6, 6], "uv": [0, 40]}
					]
				},
				{
					"name": "bone4",
					"pivot": [0, 0, 0]
				},
				{
					"name": "right_2",
					"parent": "bone4",
					"pivot": [-2.25, 2, -7.75],
					"rotation": [0, 5, 0],
					"cubes": [
						{"origin": [-3.25, 3.5, -16.75], "size": [3, 0, 10], "pivot": [-2.25, 2, -7.75], "rotation": [0, -2.5, 0], "uv": [0, 0]},
						{"origin": [-3.25, 2.5, -12.75], "size": [2, 2, 6], "pivot": [-2.25, 2, -7.75], "rotation": [0, -2.5, 0], "uv": [0, 4]}
					]
				},
				{
					"name": "left_2",
					"parent": "bone4",
					"pivot": [2.25, 2, -7.75],
					"rotation": [0, -5, 0],
					"cubes": [
						{"origin": [0.25, 3.5, -16.75], "size": [3, 0, 10], "pivot": [2.25, 2, -7.75], "rotation": [0, 2.5, 0], "uv": [38, 23]},
						{"origin": [1.25, 2.5, -12.75], "size": [2, 2, 6], "pivot": [2.25, 2, -7.75], "rotation": [0, 2.5, 0], "uv": [31, 23]}
					]
				},
				{
					"name": "right_1",
					"parent": "bone4",
					"pivot": [-5, 2, -7],
					"cubes": [
						{"origin": [-8.25, 2.5, -16.75], "size": [2, 2, 6], "pivot": [-7.25, 2, -11.75], "rotation": [0, -2.5, 0], "uv": [36, 46]},
						{"origin": [-8.25, 3.5, -21.75], "size": [5, 0, 11], "pivot": [-7.25, 2, -11.75], "rotation": [0, -2.5, 0], "uv": [10, 23]},
						{"origin": [-6, 2, -12], "size": [3, 3, 6], "pivot": [-5, 2, -7], "rotation": [0, 32.5, 0], "uv": [44, 5]}
					]
				},
				{
					"name": "left_1",
					"parent": "bone4",
					"pivot": [5, 2, -7],
					"cubes": [
						{"origin": [6.25, 2.5, -16.75], "size": [2, 2, 6], "pivot": [7.25, 2, -11.75], "rotation": [0, 2.5, 0], "uv": [48, 27]},
						{"origin": [3.25, 3.5, -21.75], "size": [5, 0, 11], "pivot": [7.25, 2, -11.75], "rotation": [0, 2.5, 0], "uv": [29, 0]},
						{"origin": [3, 2, -12], "size": [3, 3, 6], "pivot": [5, 2, -7], "rotation": [0, -32.5, 0], "uv": [18, 46]}
					]
				}
			]
		}
	]
}